memoize/__init__.py
memoize/configuration.py
memoize/entry.py
memoize/entrybuilder.py
memoize/eviction.py
memoize/exceptions.py
memoize/invalidation.py
memoize/key.py
memoize/postprocessing.py
memoize/serde.py
memoize/statuses.py
memoize/storage.py
memoize/wrapper.py
py_memoize-3.1.1.dist-info/LICENCE
py_memoize-3.1.1.dist-info/METADATA
py_memoize-3.1.1.dist-info/WHEEL
py_memoize-3.1.1.dist-info/top_level.txt
py_memoize-3.1.1.dist-info/RECORD
