Metadata-Version: 2.1
Name: py-memoize
Version: 3.1.1
Summary: Caching library for asynchronous Python applications (both based on asyncio and Tornado) that handles dogpiling properly and provides a configurable & extensible API.
Home-page: https://github.com/DreamLab/memoize
Author: Michal Zmuda
Author-email: zmu.michal@gmail.com
Maintainer: DreamLab
License: Apache License 2.0
Keywords: python cache tornado asyncio
Platform: Any
Classifier: Topic :: Software Development :: Libraries
Classifier: Programming Language :: Python :: 3
Classifier: Programming Language :: Python :: 3 :: Only
Classifier: Programming Language :: Python :: 3.7
Classifier: Programming Language :: Python :: 3.8
Classifier: Programming Language :: Python :: 3.9
Classifier: Programming Language :: Python :: 3.10
Classifier: Programming Language :: Python :: 3.11
Classifier: Programming Language :: Python :: 3.12
Classifier: Framework :: AsyncIO
Classifier: Intended Audience :: Developers
License-File: LICENCE
Provides-Extra: ujson
Requires-Dist: ujson<2,>=1.35; extra == "ujson"
